<?xml version="1.0" encoding="utf-8"?>
<search>
  
  
  
  <entry>
    <title>《绝地物资》第四章&amp;第五章</title>
    <link href="/2024/05/11/%E3%80%8A%E7%BB%9D%E5%9C%B0%E7%89%A9%E8%B5%84%E3%80%8B%E7%AC%AC%E5%9B%9B%E7%AB%A0/"/>
    <url>/2024/05/11/%E3%80%8A%E7%BB%9D%E5%9C%B0%E7%89%A9%E8%B5%84%E3%80%8B%E7%AC%AC%E5%9B%9B%E7%AB%A0/</url>
    
    <content type="html"><![CDATA[<h2 id="第四章-我拿筷子…"><a href="#第四章-我拿筷子…" class="headerlink" title="第四章 我拿筷子…"></a>第四章 我拿筷子…</h2><p>（前提：怕有的没看小说前传的童鞋看不懂这章这里说一下，这章开始就进入主线了，主线剧情就是叶天所在的和平暖暖真人特别版内，其他人获取物资的等级降低100倍，只有他不变！！！）<br>（今天没啥事，爆更，连更两章）<br>咻<del>咻咻咻</del><br>叶天站在飞行器上往G港猛攻<br>这时 G港<br>同道中人“帝”也在！<br>只不过，人实在太多了，他只能苟在里G港800米的一个撤硕里<br>但撤硕里的东西，让他眼前一亮<br>“您获得武器：筷子x1，品质：蓝色（破损不堪）”<br>“终极技能：筷子夹水泥”<br>“使用终极技能需要浪费水泥x1”<br>“目前持有水泥数量x10”<br>有了这武器，ID叫“帝”的玩家基本就可以称霸G港了<br>毕竟前期普通玩家是捡不到什么东西的<br>但谁想到，G港还有叶天这个挂B！</p><h2 id="第五章-掌管物资的神"><a href="#第五章-掌管物资的神" class="headerlink" title="第五章 掌管物资的神"></a>第五章 掌管物资的神</h2><p>叶天开着车，到了G港<br>听着附近一堆脚步声，叶天不禁头皮发麻<br>“看来只好去房区那边搜搜了”</p><p>走着走着，叶天还是走进了一个撤硕<br>毕竟外面人有点多，还是躲到这里看看作战平板好了<br>看了一看<br>走近一看<br>只有一把R-54188左轮手枪<br>“额…”<br>叶天又又又沉默了<br>不是？<br>就刷出来个这？<br>这跟答辩有啥区别啊？</p><p>但是想了一会，拿着还是比不拿好<br>手无寸铁跟人家打，你去当拳王啊？<br>“您已获取 左轮手枪R-54188 品质：金色（崭新出厂）”<br>“这破玩意还金色品质？”<br>“我都不想要”</p>]]></content>
    
    
    
    <tags>
      
      <tag>小说</tag>
      
    </tags>
    
  </entry>
  
  
  
  <entry>
    <title>声明</title>
    <link href="/2024/05/10/%E5%A3%B0%E6%98%8E/"/>
    <url>/2024/05/10/%E5%A3%B0%E6%98%8E/</url>
    
    <content type="html"><![CDATA[<h2 id="声明"><a href="#声明" class="headerlink" title="声明"></a>声明</h2><p>hi这里是餳銳<br>在这篇文章中说一下<br>小说《绝地物资》可能会不定期停更<br>具体原因就是我回北京之后没有电脑往博客上上传小说文件了<br>但是创作会继续<br>所以说博客上停更了之后不代表真正停更<br>后续也会想办法正常更新<br>可能我回家之后有电脑了就爆更一下<br>谢谢所有支持《绝地物资》的老铁 有啥意见直接在评论区直接提就行 评论功能已经上线了<br>（第三章正在写 别催<br>（第二章有点错别字和剧情缺陷啥的 已经改了感兴趣可以重新看一遍</p>]]></content>
    
    
    
    <tags>
      
      <tag>小说</tag>
      
    </tags>
    
  </entry>
  
  
  
  <entry>
    <title>《绝地物资》第三章</title>
    <link href="/2024/05/10/%E3%80%8A%E7%BB%9D%E5%9C%B0%E7%89%A9%E8%B5%84%E3%80%8B%E7%AC%AC%E4%B8%89%E7%AB%A0/"/>
    <url>/2024/05/10/%E3%80%8A%E7%BB%9D%E5%9C%B0%E7%89%A9%E8%B5%84%E3%80%8B%E7%AC%AC%E4%B8%89%E7%AB%A0/</url>
    
    <content type="html"><![CDATA[<h2 id="第三章-对战"><a href="#第三章-对战" class="headerlink" title="第三章 对战"></a>第三章 对战</h2><p>领完初始背包,对讲机和作战平板，叶天上了飞机<br>虽说一局有1000人，但是组队上限也提升到了10人，并且可以自由组队<br>只不过，林天并没有组队的意思<br>刚刚领完作战平板后，叶天简单看了一眼<br>从黑铁菜鸟到传奇宗师，什么段位的人都有。<br>“看来新手第一局并不是同段位的人一起玩啊” 林天想<br>发呆的功夫，平板开始微微震动<br>“野猪亨利886（黄金IV）邀请您组队！（6&#x2F;10）”<br>“褒咔（皇冠III）邀请您组队！（4&#x2F;10）”<br>“你个人机（铂金I）邀请您组队！（9&#x2F;10）”<br>……</p><p>毕竟是最强王者10星的战神，肯定是80%玩家都想和叶天玩<br>但是叶天看着眼前这么多邀请，默默的打开了组队过滤。。。<br>虽说多一个队友是一个，但是和这种段位的队友一起打，还不如没有呢<br>正翻着组队列表<br>叶天看到了一个队伍<br>“帝（最强宗师3星） 队伍人数（1&#x2F;10）”<br>组队大厅里传奇宗师的玩家队伍已经满了<br>叶天还是想和这个ID叫帝的玩家玩玩看<br>“说不定人家还能带我吃鸡呢！”<br>想着想着，叶天点击了申请加入<br>“加入成功！您可使用对讲机对话，作战平板及查看队友位置”<br>想着这大佬既然加了，叶天还挺开心<br>结果<br>“不是老弟就你这段位配和我玩吗，就我这段位和衣服是不是你的意杯紫，和你这样段位的人玩都不如我自己玩，我直接给你飞了你个人机”<br>“你已被帝踢出房间”<br>…<br>“怪不得没人跟他玩”<br>沉默了一会，叶天还是决定自己玩比较好</p><p>“飞机还有20秒起飞，请所有玩家观看跳伞指南与飞机航线”<br>“共有五架飞机按照不同的指定航线飞行，飞行结束后，飞机将自动爆炸”<br>“欸对啊！怎么跳伞我还不知道呢！”<br>叶天简单看了一眼航线，去看跳伞指南去了<br>“观看跳伞指南需支付188点卷或观看188秒广告”<br>…<br>“不是，这时候还插广告？”<br>等看完广告，飞机都炸了<br>为了安全落地，叶天只能花188点卷看了一下指南</p><p>“飞机已进入预定航线，玩家可随时离开飞机“<br>叶天看了看地图，最后决定飞到野区开车去G港</p><p>但是他还是忘记了</p><p>5架飞机，是按照5种不同的航线飞的！</p><p>（本章结束 该小说在X1ngrUiN13.github.io连载 杜绝抄袭从我做起）</p>]]></content>
    
    
    
    <tags>
      
      <tag>小说</tag>
      
    </tags>
    
  </entry>
  
  
  
  <entry>
    <title>《绝地物资》第二章</title>
    <link href="/2024/05/07/%E3%80%8A%E7%BB%9D%E5%9C%B0%E7%89%A9%E8%B5%84%E3%80%8B%E7%AC%AC%E4%BA%8C%E7%AB%A0/"/>
    <url>/2024/05/07/%E3%80%8A%E7%BB%9D%E5%9C%B0%E7%89%A9%E8%B5%84%E3%80%8B%E7%AC%AC%E4%BA%8C%E7%AB%A0/</url>
    
    <content type="html"><![CDATA[<h2 id="第二章-真人吃鸡？"><a href="#第二章-真人吃鸡？" class="headerlink" title="第二章 真人吃鸡？"></a>第二章 真人吃鸡？</h2><p>“啊..脑袋好疼”<br>叶天迷迷糊糊地从床上起来<br>“欸？这是哪里啊？”<br>他看着所在的房间<br>房间内只有一张床<br>叶天试着推开门，门没有锁。<br>推开门的一瞬间，类似和平暖暖的大厅出现在他的眼前<br>“欢迎来到和平暖暖-真人特别版！”<br>“我们聚集了200000000名玩家，其中有完全没玩过的人，普通玩家，大神玩家，主播，职业选手！”<br>“正在检测您的身份信息并同步账号信息”<br>“您可以通过战斗获得战利品来升级房间或食物”<br>…<br>叶天沉默了一会<br>“不是，那我什么时候能回到现实生活啊？”<br>…<br>没人回答<br>“看来这引导机器人是个智障”<br>引导机器人怒了<br>“不是老弟你啥意思啊，我不回答不代表我是个智障，你再这样我拿筷子夹水泥…”<br>“诶诶得得得，我错了行吧，那啥时候开始打排位，啊不是，竞赛啊？”<br>“您可以随时在大厅开始竞赛”<br>“但是找到竞赛后取消竞赛，会降低您的信用分与积分”<br>“您现在的信用分为满分1000分”<br>“您现在的积分是10086，等级最强王者10星”<br>“达到12星后可以开启晋级赛”<br>“普通竞赛死亡后无法复活，晋级赛失败可以复活”<br>（在对战中丝亡后自动进入观战房间观战队友，如果队友胜利代表全队胜利，可以免复活卡复活）<br>“也就是说，没了之后就真没了？也回不到现实世界？”<br>“是的，但您可以购买复活卡，您现在的复活卡数量x1”<br>“复活卡100000点卷1张，您现在的点卷数量为54188”<br>虽说账号数据都是叶天现实中的数据<br>但是这么一看<br>他现实生活中真没少打<br>也没少充钱<br>“得得，你甭巴巴了，直接开第一局竞赛吧！”<br>叶天虽然挺怕的<br>但是说实话，有一张复活卡，先打一局看看这个段位的人实力如何<br>之后再做打算<br>“滴~已为您找到竞赛，点击接受进入出生岛，拒绝信用分-1，积分-10”<br>“接受！”</p><p>（本章结束 该小说在X1ngrUiN13.github.io连载 杜绝抄袭从我做起）</p>]]></content>
    
    
    
    <tags>
      
      <tag>小说</tag>
      
    </tags>
    
  </entry>
  
  
  
  <entry>
    <title>《绝地物资》第一章</title>
    <link href="/2024/05/06/%E6%9C%AA%E6%9D%A5%E5%9F%8E/"/>
    <url>/2024/05/06/%E6%9C%AA%E6%9D%A5%E5%9F%8E/</url>
    
    <content type="html"><![CDATA[<h2 id="第一章-直播事故"><a href="#第一章-直播事故" class="headerlink" title="第一章 直播事故"></a>第一章 直播事故</h2><p>2038年4月<br>未来豪宅27号楼301<br>叶天，退役职业选手，现在改行做主播<br>他看了看手机上的时间，7点48，马上开始直播<br>趁着还有些时间，叶天点了份无人机外卖</p><p>十分钟后<br>“欸不是，这无人机炸路上了吗？怎么还没送过来”<br>在未来城这座城市，外卖大多数由无人机配送，配送时间大大缩短至5~10分钟<br>况且他点的还是离家1公里的一家店<br>不应该啊？？？<br>眼看着直播时间到了，叶天只好硬着头皮开始直播<br>看来只能在直播玩游戏的时候找地方苟着，抽空吃外卖了。<br>8：00，准时开始直播<br>“Hello大家好我是叶天，今天我们还是随机枪械随机地图，大家…”</p><p>说着说着，<br>门铃响了<br>“您的外卖到了，请出来确认一下身份”<br>为了防止外卖被偷，无论人或无人机配送时都需要确认接受外卖人身份与指定接收人身份是否一致。<br>“等一下哈家人们，我取一下外卖，马上回来！”<br>说着，叶天走到门前，打开了门<br>开门的一瞬间，叶天突然想起<br>我..点的不是无人机外卖吗？<br>但是，为时已晚。<br>砰！</p>]]></content>
    
    
    
    <tags>
      
      <tag>小说</tag>
      
    </tags>
    
  </entry>
  
  
  
  <entry>
    <title>小说前传</title>
    <link href="/2024/05/06/%E5%B0%8F%E8%AF%B4%E5%89%8D%E4%BC%A0/"/>
    <url>/2024/05/06/%E5%B0%8F%E8%AF%B4%E5%89%8D%E4%BC%A0/</url>
    
    <content type="html"><![CDATA[<h2 id="hi大家好这里是餳銳经过了半个小时的努力博客终于上线了这也是我博客的第一篇文章想了想-还是把最近写的小说投到这上面吧后续也会更新一些其他内容至于要写的小说嘛这里就讲一讲吧"><a href="#hi大家好这里是餳銳经过了半个小时的努力博客终于上线了这也是我博客的第一篇文章想了想-还是把最近写的小说投到这上面吧后续也会更新一些其他内容至于要写的小说嘛这里就讲一讲吧" class="headerlink" title="hi大家好这里是餳銳经过了半个小时的努力博客终于上线了这也是我博客的第一篇文章想了想 还是把最近写的小说投到这上面吧后续也会更新一些其他内容至于要写的小说嘛这里就讲一讲吧"></a>hi大家好这里是餳銳<br>经过了半个小时的努力博客终于上线了<br>这也是我博客的第一篇文章<br>想了想 还是把最近写的小说投到这上面吧<br>后续也会更新一些其他内容<br>至于要写的小说嘛<br>这里就讲一讲吧</h2><p>《绝地物资》<br>by 餳銳<br>（原创小说请支持正版杜绝抄袭）<br>这篇小说讲的是主人公叶天不小心穿越进热门游戏“和平暖暖”中<br>在这款游戏中，所有人能获取的物资等级降低100倍，只有他不变！<br>【在X1ngrUiN13.github.io连载 杜绝抄袭从我做起】</p>]]></content>
    
    
    
    <tags>
      
      <tag>小说</tag>
      
    </tags>
    
  </entry>
  
  
  
  <entry>
    <title>Hello World</title>
    <link href="/2024/05/06/hello-world/"/>
    <url>/2024/05/06/hello-world/</url>
    
    <content type="html"><![CDATA[<p>Welcome to <a href="https://hexo.io/">Hexo</a>! This is your very first post. Check <a href="https://hexo.io/docs/">documentation</a> for more info. If you get any problems when using Hexo, you can find the answer in <a href="https://hexo.io/docs/troubleshooting.html">troubleshooting</a> or you can ask me on <a href="https://github.com/hexojs/hexo/issues">GitHub</a>.</p><h2 id="Quick-Start"><a href="#Quick-Start" class="headerlink" title="Quick Start"></a>Quick Start</h2><h3 id="Create-a-new-post"><a href="#Create-a-new-post" class="headerlink" title="Create a new post"></a>Create a new post</h3><figure class="highlight bash"><table><tr><td class="gutter"><pre><span class="line">1</span><br></pre></td><td class="code"><pre><span class="line">$ hexo new <span class="string">&quot;My New Post&quot;</span></span><br></pre></td></tr></table></figure><p>More info: <a href="https://hexo.io/docs/writing.html">Writing</a></p><h3 id="Run-server"><a href="#Run-server" class="headerlink" title="Run server"></a>Run server</h3><figure class="highlight bash"><table><tr><td class="gutter"><pre><span class="line">1</span><br></pre></td><td class="code"><pre><span class="line">$ hexo server</span><br></pre></td></tr></table></figure><p>More info: <a href="https://hexo.io/docs/server.html">Server</a></p><h3 id="Generate-static-files"><a href="#Generate-static-files" class="headerlink" title="Generate static files"></a>Generate static files</h3><figure class="highlight bash"><table><tr><td class="gutter"><pre><span class="line">1</span><br></pre></td><td class="code"><pre><span class="line">$ hexo generate</span><br></pre></td></tr></table></figure><p>More info: <a href="https://hexo.io/docs/generating.html">Generating</a></p><h3 id="Deploy-to-remote-sites"><a href="#Deploy-to-remote-sites" class="headerlink" title="Deploy to remote sites"></a>Deploy to remote sites</h3><figure class="highlight bash"><table><tr><td class="gutter"><pre><span class="line">1</span><br></pre></td><td class="code"><pre><span class="line">$ hexo deploy</span><br></pre></td></tr></table></figure><p>More info: <a href="https://hexo.io/docs/one-command-deployment.html">Deployment</a></p>]]></content>
    
    
    
  </entry>
  
  
  
  
</search>
